__init__.py
setup.py
version.py
examples/__init__.py
examples/camds/uncabled.ipynb
examples/ctdbp/__init__.py
examples/ctdbp/combine_mooring_ctdbp.py
examples/ctdbp/recovered_host_ctdbp.py
examples/ctdbp/recovered_inst_ctdbp.py
examples/ctdbp/telemetered_ctdbp.py
examples/ctdpf/__init__.py
examples/ctdpf/cspp_ctdpf.py
examples/dosta/__init__.py
examples/dosta/combine_mooring_dosta.py
examples/dosta/recovered_host_ctdbp_dosta.py
examples/dosta/recovered_host_solo_dosta.py
examples/dosta/recovered_inst_ctdbp_dosta.py
examples/dosta/telemetered_ctdbp_dosta.py
examples/dosta/telemetered_solo_dosta.py
examples/flort/__init__.py
examples/flort/cabled_profiler_flort.py
examples/flort/cspp_flort.py
examples/flort/recovered_host_flort.py
examples/flort/recovered_inst_flort.py
examples/flort/telemetered_flort.py
examples/flort/wfp_flort.py
examples/metbk/__init__.py
examples/metbk/recovered_host_metbk.py
examples/metbk/telemetered_bulk_flux.py
examples/metbk/telemetered_metbk.py
examples/notebooks/m2m_explorations.ipynb
examples/notebooks/dosta/ooiea_cabled_dosta_processing.ipynb
examples/notebooks/dosta/ooiea_dosta_annotations_hitl_qc.ipynb
examples/notebooks/dosta/ooiea_dosta_quality_assessments.ipynb
examples/notebooks/dosta/ooiea_uncabled_dosta_data.ipynb
examples/notebooks/fdchp/.gitignore
examples/notebooks/fdchp/FdchpExample.ipynb
examples/notebooks/fdchp/ProcessFdchpRaw.ipynb
examples/notebooks/ifcb/combining_ifcb_and_environmental.ipynb
examples/notebooks/optaa/acs137_20210302_pre_deployment_adat.csv
examples/notebooks/optaa/acs137_20210302_pre_deployment_cdat.csv
examples/notebooks/optaa/process_kdata_cabled_profiler_ce04osps.ipynb
examples/notebooks/optaa/process_kdata_cabled_profiler_rs01sbps.ipynb
examples/notebooks/optaa/process_kdata_optaa.ipynb
examples/notebooks/optaa/process_thredds_optaa.ipynb
examples/notebooks/optaa/process_thredds_optaa_cspp.ipynb
examples/notebooks/optaa/processing_workflow_using_the_cspp_optaa.ipynb
ooi_data_explorations-0.2.3.dist-info/METADATA
ooi_data_explorations-0.2.3.dist-info/WHEEL
ooi_data_explorations-0.2.3.dist-info/licenses/LICENSE.txt
ooi_data_explorations-0.2.3.dist-info/RECORD
