Metadata-Version: 2.4
Name: ooi_data_explorations
Version: 0.2.3
Summary: Tools for interacting with OOI data, including downloading, cleaning, and visualizing.
Author-email: Christopher Wingard <chris.wingard@oregonstate.edu>, Andrew Reed <areed@whoi.edu>, Joffrey Peters <joffreyp@gmail.com>
Maintainer-email: Christopher Wingard <chris.wingard@oregonstate.edu>, Andrew Reed <areed@whoi.edu>, Joffrey Peters <joffreyp@gmail.com>
License-Expression: MIT
License-File: LICENSE.txt
Keywords: Ocean Observatories Initiative,URL parameters,jupyter_server
Classifier: Development Status :: 3 - Alpha
Classifier: Framework :: Jupyter
Classifier: Intended Audience :: Developers
Classifier: Intended Audience :: Science/Research
Classifier: Intended Audience :: System Administrators
Classifier: License :: OSI Approved :: BSD License
Classifier: Programming Language :: Python
Classifier: Programming Language :: Python :: 3
Classifier: Programming Language :: Python :: 3 :: Only
Classifier: Programming Language :: Python :: 3.9
Classifier: Programming Language :: Python :: 3.10
Classifier: Programming Language :: Python :: 3.11
Classifier: Programming Language :: Python :: 3.12
Requires-Python: >=3.9
Requires-Dist: beautifulsoup4
Requires-Dist: dask
Requires-Dist: gsw
Requires-Dist: h5netcdf
Requires-Dist: matplotlib
Requires-Dist: munch
Requires-Dist: netcdf4
Requires-Dist: ntplib
Requires-Dist: numpy
Requires-Dist: pandas
Requires-Dist: pyyaml
Requires-Dist: requests
Requires-Dist: tqdm
Requires-Dist: urllib3
Requires-Dist: xarray[accel]
Provides-Extra: dev
Requires-Dist: build; extra == 'dev'
Requires-Dist: hatch; extra == 'dev'
Requires-Dist: ipykernel; extra == 'dev'
Requires-Dist: pre-commit; extra == 'dev'
Requires-Dist: requests; extra == 'dev'
Requires-Dist: ruff; extra == 'dev'
